guard.py
guard-1.0.1.dist-info/DESCRIPTION.rst
guard-1.0.1.dist-info/METADATA
guard-1.0.1.dist-info/pydist.json
guard-1.0.1.dist-info/RECORD
guard-1.0.1.dist-info/top_level.txt
guard-1.0.1.dist-info/WHEEL
