Metadata-Version: 2.0
Name: guard
Version: 1.0.1
Summary: WSGI Middlewares for Web Application Security
Home-page: https://github.com/dstufft/guard
Author: Donald Stufft
Author-email: donald@stufft.io
License: Apache License v2.0
Platform: UNKNOWN
Classifier: License :: OSI Approved :: Apache Software License
Classifier: Programming Language :: Python
Classifier: Programming Language :: Python :: 2
Classifier: Programming Language :: Python :: 2.6
Classifier: Programming Language :: Python :: 2.7
Classifier: Programming Language :: Python :: 3
Classifier: Programming Language :: Python :: 3.2
Classifier: Programming Language :: Python :: 3.3
